LICENSE
README.md
setup.py
airporticao/__init__.py
airporticao/airporticao.py
airporticao.egg-info/PKG-INFO
airporticao.egg-info/SOURCES.txt
airporticao.egg-info/dependency_links.txt
airporticao.egg-info/not-zip-safe
airporticao.egg-info/requires.txt
airporticao.egg-info/top_level.txt